yt_channel_scraper/__init__.py
yt_channel_scraper/youtube_downloader.py
yt_channel_scraper/yt_channel_scraper.py
yt_channel_scraper-0.1.1.dist-info/LICENSE
yt_channel_scraper-0.1.1.dist-info/METADATA
yt_channel_scraper-0.1.1.dist-info/WHEEL
yt_channel_scraper-0.1.1.dist-info/top_level.txt
yt_channel_scraper-0.1.1.dist-info/RECORD
