Metadata-Version: 2.1
Name: yt-channel-scraper
Version: 0.1.1
Summary: All in one Youtube Solution for python. Scrap, Fetch, Download anything from a Youtube Channel, Video.
Author: Priyanshu Panwar
Author-email: priyanshu009ch@gmail.com
Project-URL: Source, https://github.com/priyanshu-panwar/yt-channel-scraper
License-File: LICENSE
Requires-Dist: scrapetube
Requires-Dist: youtube-transcript-api
Requires-Dist: requests
Requires-Dist: beautifulsoup4
Requires-Dist: pytube
